midiscripter/__init__.py
midiscripter/ableton_remote/UserConfiguration.txt
midiscripter/ableton_remote/__init__.py
midiscripter/ableton_remote/ableton_msg.py
midiscripter/ableton_remote/ableton_port.py
midiscripter/ableton_remote/remote_script_midi_mapping.py
midiscripter/base/__init__.py
midiscripter/base/msg_base.py
midiscripter/base/port_base.py
midiscripter/cli/__init__.py
midiscripter/cli/starters.py
midiscripter/file_event/__init__.py
midiscripter/file_event/file_event_msg.py
midiscripter/file_event/file_event_port.py
midiscripter/gui/__init__.py
midiscripter/gui/app.py
midiscripter/gui/color_theme.py
midiscripter/gui/log_widget.py
midiscripter/gui/main_window.py
midiscripter/gui/menu_bar.py
midiscripter/gui/message_sender.py
midiscripter/gui/ports_widget.py
midiscripter/gui/saved_state_controls.py
midiscripter/gui/gui_widgets/__init__.py
midiscripter/gui/gui_widgets/button.py
midiscripter/gui/gui_widgets/gui_msg.py
midiscripter/gui/gui_widgets/gui_widget_base.py
midiscripter/gui/gui_widgets/layout.py
midiscripter/gui/gui_widgets/list.py
midiscripter/gui/gui_widgets/mixins.py
midiscripter/gui/gui_widgets/slider.py
midiscripter/gui/gui_widgets/text.py
midiscripter/keyboard/__init__.py
midiscripter/keyboard/keyboard_msg.py
midiscripter/keyboard/keyboard_port.py
midiscripter/logger/__init__.py
midiscripter/logger/console.py
midiscripter/logger/html.py
midiscripter/logger/log_obj.py
midiscripter/metronome/__init__.py
midiscripter/metronome/metronome_port.py
midiscripter/midi/__init__.py
midiscripter/midi/midi_msg.py
midiscripter/midi/midi_note_data.py
midiscripter/midi/midi_port.py
midiscripter/midi/midi_ports_changed.py
midiscripter/midi/teVirtualMIDI.py
midiscripter/mouse/__init__.py
midiscripter/mouse/mouse_msg.py
midiscripter/mouse/mouse_port.py
midiscripter/osc/__init__.py
midiscripter/osc/osc_msg.py
midiscripter/osc/osc_port.py
midiscripter/resources/icon.ico
midiscripter/resources/icon.svg
midiscripter/shared/__init__.py
midiscripter-0.8.1.dist-info/METADATA
midiscripter-0.8.1.dist-info/WHEEL
midiscripter-0.8.1.dist-info/entry_points.txt
midiscripter-0.8.1.dist-info/licenses/LICENSE
midiscripter-0.8.1.dist-info/RECORD
