Metadata-Version: 2.4
Name: midiscripter
Version: 0.8.1
Summary: Framework for scripting MIDI, Open Sound Control, keyboard and mouse input and output
Project-URL: Documentation, https://maboroshy.github.io/midi-scripter
Project-URL: Issues, https://github.com/Maboroshy/midi-scripter/issues
Project-URL: Source, https://github.com/Maboroshy/midi-scripter
Author: Maboroshy
License-Expression: LGPL-3.0-or-later
License-File: LICENSE
Keywords: MIDI,OSC,automation,input,script
Classifier: Development Status :: 4 - Beta
Classifier: License :: OSI Approved :: GNU Lesser General Public License v3 (LGPLv3)
Classifier: Programming Language :: Python :: 3.11
Classifier: Programming Language :: Python :: 3.12
Classifier: Programming Language :: Python :: 3.13
Classifier: Programming Language :: Python :: 3.14
Classifier: Topic :: Multimedia :: Sound/Audio
Classifier: Topic :: Multimedia :: Sound/Audio :: MIDI
Classifier: Topic :: Software Development :: Libraries :: Python Modules
Requires-Python: >=3.11
Requires-Dist: colorama~=0.4
Requires-Dist: pynput~=1.7
Requires-Dist: pyside6-essentials>6.5
Requires-Dist: python-osc~=1.7
Requires-Dist: python-rtmidi~=1.5
Requires-Dist: pywin32; platform_system == 'Windows'
Requires-Dist: watchdog~=4.0
Provides-Extra: dev
Requires-Dist: ruff; extra == 'dev'
Provides-Extra: doc
Requires-Dist: black; extra == 'doc'
Requires-Dist: griffe-inherited-docstrings; extra == 'doc'
Requires-Dist: mkdocs-material; extra == 'doc'
Requires-Dist: mkdocstrings; extra == 'doc'
